higlass_schema/__init__.py
higlass_schema/cli.py
higlass_schema/schema.py
higlass_schema/utils.py
higlass_schema-0.2.1.dist-info/METADATA
higlass_schema-0.2.1.dist-info/WHEEL
higlass_schema-0.2.1.dist-info/entry_points.txt
higlass_schema-0.2.1.dist-info/licenses/LICENSE
higlass_schema-0.2.1.dist-info/RECORD
