Metadata-Version: 2.3
Name: higlass-schema
Version: 0.2.1
Summary: Pydantic models for HiGlass
Project-URL: homepage, https://github.com/higlass/higlass-schema
Author-email: Trevor Manz <trevor.j.manz@gmail.com>
License: MIT
Requires-Python: >=3.8
Requires-Dist: pydantic>=2.0
Requires-Dist: rich>=13.0.0
